COPYING
LICENSE.txt
MANIFEST.in
README.rst
setup.py
docs/R.rst
docs/README.rst
docs/UseAsRemoteTerminal.rst
docs/UsingGraphicalFeatures.rst
docs/advanced.rst
docs/contact.rst
docs/contents.rst
docs/extend.rst
docs/features.rst
docs/format.rst
docs/implementation.rst
docs/progressive.rst
docs/release-notes.rst
docs/remote.rst
docs/screenshots.rst
docs/start.rst
docs/talks.rst
docs/tracing.rst
docs/troubleshooting.rst
docs/virtual-lab.rst
docs/virtual-setup.rst
docs/widgets.rst
docs/_templates/index.html
docs/_templates/indexsidebar.html
docs/_templates/layout.html
docs/_templates.sav/layout.html
docs/_themes.sav/sphinx-bootstrap/globaltoc.html
docs/_themes.sav/sphinx-bootstrap/layout.html
docs/_themes.sav/sphinx-bootstrap/localtoc.html
graphterm/__init__.py
graphterm/about.py
graphterm/daemon.py
graphterm/episode4.txt
graphterm/episodeIV.txt
graphterm/gotrace.py
graphterm/gterm_setup.py
graphterm/gtermhost.py
graphterm/gtermserver.py
graphterm/lineterm.py
graphterm/optconfig.py
graphterm/ordereddict.py
graphterm/otrace.py
graphterm/packetserver.py
graphterm/simplepam.py
graphterm/version.py
graphterm.egg-info/PKG-INFO
graphterm.egg-info/SOURCES.txt
graphterm.egg-info/dependency_links.txt
graphterm.egg-info/entry_points.txt
graphterm.egg-info/requires.txt
graphterm.egg-info/top_level.txt
graphterm/bin/__init__.py
graphterm/bin/bokeh_demo.py
graphterm/bin/d3cloud
graphterm/bin/ec2common.py
graphterm/bin/ec2launch
graphterm/bin/ec2list
graphterm/bin/ec2scp
graphterm/bin/ec2ssh
graphterm/bin/gadmin
graphterm/bin/galiases
graphterm/bin/gauth.py
graphterm/bin/gbrowse
graphterm/bin/gchat
graphterm/bin/gcp
graphterm/bin/gdownload
graphterm/bin/gfeed
graphterm/bin/gframe
graphterm/bin/gimage
graphterm/bin/gimg.sh
graphterm/bin/gipynb
graphterm/bin/gipython
graphterm/bin/gjs
graphterm/bin/gload
graphterm/bin/gls
graphterm/bin/gls.sh
graphterm/bin/gmatplot.py
graphterm/bin/gmenu
graphterm/bin/gnbserver
graphterm/bin/gncplot
graphterm/bin/gopen
graphterm/bin/gprofile
graphterm/bin/gpylab.py
graphterm/bin/gpython
graphterm/bin/gqrcode
graphterm/bin/graphtermd
graphterm/bin/greveal
graphterm/bin/gscript
graphterm/bin/gsh
graphterm/bin/gshow.ncl
graphterm/bin/gshow.pro
