Metadata-Version: 1.1
Name: graphterm
Version: 0.57.0
Summary: GraphTerm: A Graphical Terminal Interface
Home-page: http://code.mindmeldr.com/graphterm
Author: Ramalingam Saravanan
Author-email: sarava@sarava.net
License: BSD License
Keywords: command line interface,console,multiplexer,remote desktop,terminal,terminal emulator,xterm
Platform: UNKNOWN
Classifier: Development Status :: 3 - Alpha
Classifier: Environment :: Console
Classifier: Intended Audience :: Developers
Classifier: Intended Audience :: End Users/Desktop
Classifier: Intended Audience :: Information Technology
Classifier: Intended Audience :: System Administrators
Classifier: License :: OSI Approved :: BSD License
Classifier: Operating System :: OS Independent
Classifier: Programming Language :: Python
Classifier: Topic :: System :: Shells
Classifier: Topic :: Terminals :: Terminal Emulators/X Terminals
Classifier: Topic :: Utilities
